dataclasses_struct/__init__.py
dataclasses_struct/_typing.py
dataclasses_struct/dataclass.py
dataclasses_struct/field.py
dataclasses_struct/py.typed
dataclasses_struct/types.py
dataclasses_struct/ext/__init__.py
dataclasses_struct/ext/mypy_plugin.py
dataclasses_struct-1.4.0.dist-info/METADATA
dataclasses_struct-1.4.0.dist-info/WHEEL
dataclasses_struct-1.4.0.dist-info/licenses/LICENSE
dataclasses_struct-1.4.0.dist-info/RECORD
