Metadata-Version: 2.4
Name: dataclasses-struct
Version: 1.4.0
Summary: Converting dataclasses to and from fixed-length binary data using struct
Project-URL: Homepage, https://github.com/harrymander/dataclasses-struct
Project-URL: Repository, https://github.com/harrymander/dataclasses-struct
Project-URL: Documentation, https://harrymander.xyz/dataclasses-struct
Author-email: Harry Mander <harrymander96@gmail.com>
License-File: LICENSE
Classifier: Development Status :: 4 - Beta
Classifier: Intended Audience :: Developers
Classifier: Intended Audience :: Information Technology
Classifier: License :: OSI Approved :: MIT License
Classifier: Operating System :: OS Independent
Classifier: Programming Language :: Python
Classifier: Programming Language :: Python :: 3
Classifier: Programming Language :: Python :: 3 :: Only
Classifier: Programming Language :: Python :: 3.9
Classifier: Programming Language :: Python :: 3.10
Classifier: Programming Language :: Python :: 3.11
Classifier: Programming Language :: Python :: 3.12
Classifier: Programming Language :: Python :: 3.13
Classifier: Programming Language :: Python :: Implementation :: CPython
Classifier: Programming Language :: Python :: Implementation :: PyPy
Classifier: Topic :: Software Development :: Libraries :: Python Modules
Classifier: Typing :: Typed
Requires-Python: >=3.9.0
Requires-Dist: typing-extensions>=4.12.2; python_full_version < '3.11'
